{
    "metadata": {
        "photo": {
            "id": "2899223045",
            "secret": "2655e3fcc1",
            "server": "3063",
            "farm": 4,
            "dateuploaded": "1222721061",
            "isfavorite": 0,
            "license": "3",
            "safety_level": "0",
            "rotation": 0,
            "originalsecret": "d69de2d3e7",
            "originalformat": "jpg",
            "owner": {
                "nsid": "29072716@N04",
                "username": "Cushing Memorial Library and Archives, Texas A&M",
                "realname": "",
                "location": "",
                "iconserver": "3100",
                "iconfarm": 4,
                "path_alias": "cushinglibrary",
                "gift": {
                    "gift_eligible": true,
                    "eligible_durations": [
                        "year",
                        "month",
                        "week"
                    ],
                    "new_flow": true
                }
            },
            "title": {
                "_content": "YMCA - 57"
            },
            "description": {
                "_content": "<b>Title: </b>YMCA - 57 \n<b>Digital Publisher: </b>Digital: Cushing Memorial Library and Archives, Texas A&amp;M University, College Station, Texas \n<b>Physical Publisher: </b>Physical: Cushing Memorial Library and Archives, Texas A&amp;M University \n<b>Description:</b> Barber Sho; Buildings: YMCA \n<b>Date Issued:</b> 2005-06-30 \n<b>Dimensions: </b>5.317 x 3.268 inches \n<b>Type: </b>image \n<b>Identifier:</b> YMCA 1; Photograph Location: Building Photo; Reference Number: 902 \n<b>Rights: </b>It is the users responsibility to secure permission from the copyright holders for publication of any materials. Permission must be obtained in writing prior to publication. Please contact the Cushing Memorial Library for further information \n"
            },
            "visibility": {
                "ispublic": 1,
                "isfriend": 0,
                "isfamily": 0
            },
            "dates": {
                "posted": "1222721061",
                "taken": "2008-09-29 13:44:21",
                "takengranularity": 0,
                "takenunknown": 0,
                "lastupdate": "1421775393"
            },
            "views": "560",
            "editability": {
                "cancomment": 0,
                "canaddmeta": 0
            },
            "publiceditability": {
                "cancomment": 1,
                "canaddmeta": 1
            },
            "usage": {
                "candownload": 1,
                "canblog": 0,
                "canprint": 0,
                "canshare": 1
            },
            "comments": {
                "_content": "0"
            },
            "notes": {
                "note": []
            },
            "people": {
                "haspeople": 0
            },
            "tags": {
                "tag": []
            },
            "urls": {
                "url": [
                    {
                        "type": "photopage",
                        "_content": "https://www.flickr.com/photos/cushinglibrary/2899223045/"
                    }
                ]
            },
            "media": "photo",
            "descriptive_metadata": {
                "Title": "YMCA - 57",
                "Digital Publisher": "Digital: Cushing Memorial Library and Archives, Texas A&amp;M University, College Station, Texas",
                "Physical Publisher": "Physical: Cushing Memorial Library and Archives, Texas A&amp;M University",
                "Description": "Barber Sho; Buildings: YMCA",
                "Date Issued": "2005-06-30",
                "Dimensions": "5.317 x 3.268 inches",
                "Type": "image",
                "Identifier": "YMCA 1; Photograph Location: Building Photo; Reference Number: 902",
                "Rights": "It is the users responsibility to secure permission from the copyright holders for publication of any materials. Permission must be obtained in writing prior to publication. Please contact the Cushing Memorial Library for further information"
            }
        },
        "stat": "ok"
    },
    "exif": {
        "photo": {
            "id": "2899223045",
            "secret": "2655e3fcc1",
            "server": "3063",
            "farm": 4,
            "camera": "",
            "exif": [
                {
                    "tagspace": "JFIF",
                    "tagspaceid": 0,
                    "tag": "JFIFVersion",
                    "label": "JFIFVersion",
                    "raw": {
                        "_content": "1.02"
                    }
                },
                {
                    "tagspace": "JFIF",
                    "tagspaceid": 0,
                    "tag": "ResolutionUnit",
                    "label": "Resolution Unit",
                    "raw": {
                        "_content": "inches"
                    }
                },
                {
                    "tagspace": "JFIF",
                    "tagspaceid": 0,
                    "tag": "XResolution",
                    "label": "X-Resolution",
                    "raw": {
                        "_content": "400"
                    },
                    "clean": {
                        "_content": "400 dpi"
                    }
                },
                {
                    "tagspace": "JFIF",
                    "tagspaceid": 0,
                    "tag": "YResolution",
                    "label": "Y-Resolution",
                    "raw": {
                        "_content": "400"
                    },
                    "clean": {
                        "_content": "400 dpi"
                    }
                }
            ]
        },
        "stat": "ok"
    },
    "comments": {
        "comments": {
            "photo_id": "2899223045"
        },
        "stat": "ok"
    },
    "sizes": {
        "sizes": {
            "canblog": 0,
            "canprint": 0,
            "candownload": 1,
            "size": [
                {
                    "label": "Square",
                    "width": 75,
                    "height": 75,
                    "source": "https://live.staticflickr.com/3063/2899223045_2655e3fcc1_s.jpg",
                    "url": "https://www.flickr.com/photos/cushinglibrary/2899223045/sizes/sq/",
                    "media": "photo"
                },
                {
                    "label": "Large Square",
                    "width": 150,
                    "height": 150,
                    "source": "https://live.staticflickr.com/3063/2899223045_2655e3fcc1_q.jpg",
                    "url": "https://www.flickr.com/photos/cushinglibrary/2899223045/sizes/q/",
                    "media": "photo"
                },
                {
                    "label": "Thumbnail",
                    "width": 100,
                    "height": 61,
                    "source": "https://live.staticflickr.com/3063/2899223045_2655e3fcc1_t.jpg",
                    "url": "https://www.flickr.com/photos/cushinglibrary/2899223045/sizes/t/",
                    "media": "photo"
                },
                {
                    "label": "Small",
                    "width": 240,
                    "height": 147,
                    "source": "https://live.staticflickr.com/3063/2899223045_2655e3fcc1_m.jpg",
                    "url": "https://www.flickr.com/photos/cushinglibrary/2899223045/sizes/s/",
                    "media": "photo"
                },
                {
                    "label": "Small 320",
                    "width": 320,
                    "height": 197,
                    "source": "https://live.staticflickr.com/3063/2899223045_2655e3fcc1_n.jpg",
                    "url": "https://www.flickr.com/photos/cushinglibrary/2899223045/sizes/n/",
                    "media": "photo"
                },
                {
                    "label": "Small 400",
                    "width": 400,
                    "height": 246,
                    "source": "https://live.staticflickr.com/3063/2899223045_2655e3fcc1_w.jpg",
                    "url": "https://www.flickr.com/photos/cushinglibrary/2899223045/sizes/w/",
                    "media": "photo"
                },
                {
                    "label": "Medium",
                    "width": 500,
                    "height": 307,
                    "source": "https://live.staticflickr.com/3063/2899223045_2655e3fcc1.jpg",
                    "url": "https://www.flickr.com/photos/cushinglibrary/2899223045/sizes/m/",
                    "media": "photo"
                },
                {
                    "label": "Medium 640",
                    "width": 640,
                    "height": 393,
                    "source": "https://live.staticflickr.com/3063/2899223045_2655e3fcc1_z.jpg",
                    "url": "https://www.flickr.com/photos/cushinglibrary/2899223045/sizes/z/",
                    "media": "photo"
                },
                {
                    "label": "Medium 800",
                    "width": 800,
                    "height": 492,
                    "source": "https://live.staticflickr.com/3063/2899223045_2655e3fcc1_c.jpg",
                    "url": "https://www.flickr.com/photos/cushinglibrary/2899223045/sizes/c/",
                    "media": "photo"
                },
                {
                    "label": "Large",
                    "width": 1024,
                    "height": 629,
                    "source": "https://live.staticflickr.com/3063/2899223045_2655e3fcc1_b.jpg",
                    "url": "https://www.flickr.com/photos/cushinglibrary/2899223045/sizes/l/",
                    "media": "photo"
                },
                {
                    "label": "Large 1600",
                    "width": 1600,
                    "height": 983,
                    "source": "https://live.staticflickr.com/3063/2899223045_ece2c1c616_h.jpg",
                    "url": "https://www.flickr.com/photos/cushinglibrary/2899223045/sizes/h/",
                    "media": "photo"
                },
                {
                    "label": "Large 2048",
                    "width": 2048,
                    "height": 1258,
                    "source": "https://live.staticflickr.com/3063/2899223045_66bb3035e9_k.jpg",
                    "url": "https://www.flickr.com/photos/cushinglibrary/2899223045/sizes/k/",
                    "media": "photo"
                },
                {
                    "label": "Original",
                    "width": 2127,
                    "height": 1307,
                    "source": "https://live.staticflickr.com/3063/2899223045_d69de2d3e7_o.jpg",
                    "url": "https://www.flickr.com/photos/cushinglibrary/2899223045/sizes/o/",
                    "media": "photo"
                }
            ]
        },
        "stat": "ok"
    }
}