{
    "metadata": {
        "photo": {
            "id": "3533453489",
            "secret": "77de67f3af",
            "server": "3321",
            "farm": 4,
            "dateuploaded": "1242412338",
            "isfavorite": 0,
            "license": "3",
            "safety_level": "0",
            "rotation": 0,
            "originalsecret": "c1e692b63a",
            "originalformat": "jpg",
            "owner": {
                "nsid": "29072716@N04",
                "username": "Cushing Memorial Library and Archives, Texas A&M",
                "realname": "",
                "location": "",
                "iconserver": "3100",
                "iconfarm": 4,
                "path_alias": "cushinglibrary",
                "gift": {
                    "gift_eligible": true,
                    "eligible_durations": [
                        "year",
                        "month",
                        "week"
                    ],
                    "new_flow": true
                }
            },
            "title": {
                "_content": "image-5645"
            },
            "description": {
                "_content": "<b>Creator:</b>Unknown\n <b>Reference Number:</b>    5645    \n <b>Publisher:</b>    Cushing Memorial Library and Archives, Texas A&amp;M University    \n <b>Document Type:</b>    Photograph    \n <b>Category:</b>    Athletics: Basketball - Mens - 1911-1920    \n <b>Digitization Date:</b>    2006-04-14    \n<b>Photograph Date:</b>    1913    \n<b>Dimensions:</b>    7.75 x 10 inches    \n <b>Location:</b>    Pictures: Men's Basketball 1911-1920 - 1    \n <b>Collection:</b>    Texas A&amp;M University Archives Photograph Collection    \n <b>Contact Information:</b>    Email: <a href=\"mailto:cushing-library@tamu.edu\" rel=\"noreferrer nofollow\">cushing-library@tamu.edu</a>   Phone: 979-845-1951    \n <b>Repository:</b>     Cushing Memorial Library and Archives, Texas A&amp;M University, College Station, Texas    \n <b>Restrictions:</b>     It is the users responsibility to secure permission from the copyright holders for publication of any materials. Permission must be obtained in writing prior to publication. Please contact the Cushing Library for further information.    \n"
            },
            "visibility": {
                "ispublic": 1,
                "isfriend": 0,
                "isfamily": 0
            },
            "dates": {
                "posted": "1242412338",
                "taken": "2009-05-15 11:32:18",
                "takengranularity": 0,
                "takenunknown": 0,
                "lastupdate": "1421775646"
            },
            "views": "2074",
            "editability": {
                "cancomment": 0,
                "canaddmeta": 0
            },
            "publiceditability": {
                "cancomment": 1,
                "canaddmeta": 1
            },
            "usage": {
                "candownload": 1,
                "canblog": 0,
                "canprint": 0,
                "canshare": 1
            },
            "comments": {
                "_content": "0"
            },
            "notes": {
                "note": []
            },
            "people": {
                "haspeople": 0
            },
            "tags": {
                "tag": []
            },
            "urls": {
                "url": [
                    {
                        "type": "photopage",
                        "_content": "https://www.flickr.com/photos/cushinglibrary/3533453489/"
                    }
                ]
            },
            "media": "photo",
            "descriptive_metadata": {
                "Creator": "Unknown",
                " Reference Number": "5645",
                " Publisher": "Cushing Memorial Library and Archives, Texas A&amp;M University",
                " Document Type": "Photograph",
                " Category": "Athletics: Basketball - Mens - 1911-1920",
                " Digitization Date": "2006-04-14",
                "Photograph Date": "1913",
                "Dimensions": "7.75 x 10 inches",
                " Location": "Pictures: Men's Basketball 1911-1920 - 1",
                " Collection": "Texas A&amp;M University Archives Photograph Collection",
                " Contact Information": "Email: <a href=\"mailto:cushing-library@tamu.edu\" rel=\"noreferrer nofollow\">cushing-library@tamu.edu</a>   Phone: 979-845-1951",
                " Repository": "Cushing Memorial Library and Archives, Texas A&amp;M University, College Station, Texas",
                " Restrictions": "It is the users responsibility to secure permission from the copyright holders for publication of any materials. Permission must be obtained in writing prior to publication. Please contact the Cushing Library for further information."
            }
        },
        "stat": "ok"
    },
    "exif": {
        "photo": {
            "id": "3533453489",
            "secret": "77de67f3af",
            "server": "3321",
            "farm": 4,
            "camera": "",
            "exif": [
                {
                    "tagspace": "JFIF",
                    "tagspaceid": 0,
                    "tag": "JFIFVersion",
                    "label": "JFIFVersion",
                    "raw": {
                        "_content": "1.02"
                    }
                },
                {
                    "tagspace": "JFIF",
                    "tagspaceid": 0,
                    "tag": "ResolutionUnit",
                    "label": "Resolution Unit",
                    "raw": {
                        "_content": "inches"
                    }
                },
                {
                    "tagspace": "JFIF",
                    "tagspaceid": 0,
                    "tag": "XResolution",
                    "label": "X-Resolution",
                    "raw": {
                        "_content": "400"
                    },
                    "clean": {
                        "_content": "400 dpi"
                    }
                },
                {
                    "tagspace": "JFIF",
                    "tagspaceid": 0,
                    "tag": "YResolution",
                    "label": "Y-Resolution",
                    "raw": {
                        "_content": "400"
                    },
                    "clean": {
                        "_content": "400 dpi"
                    }
                }
            ]
        },
        "stat": "ok"
    },
    "comments": {
        "comments": {
            "photo_id": "3533453489"
        },
        "stat": "ok"
    },
    "sizes": {
        "sizes": {
            "canblog": 0,
            "canprint": 0,
            "candownload": 1,
            "size": [
                {
                    "label": "Square",
                    "width": 75,
                    "height": 75,
                    "source": "https://live.staticflickr.com/3321/3533453489_77de67f3af_s.jpg",
                    "url": "https://www.flickr.com/photos/cushinglibrary/3533453489/sizes/sq/",
                    "media": "photo"
                },
                {
                    "label": "Large Square",
                    "width": 150,
                    "height": 150,
                    "source": "https://live.staticflickr.com/3321/3533453489_77de67f3af_q.jpg",
                    "url": "https://www.flickr.com/photos/cushinglibrary/3533453489/sizes/q/",
                    "media": "photo"
                },
                {
                    "label": "Thumbnail",
                    "width": 82,
                    "height": 100,
                    "source": "https://live.staticflickr.com/3321/3533453489_77de67f3af_t.jpg",
                    "url": "https://www.flickr.com/photos/cushinglibrary/3533453489/sizes/t/",
                    "media": "photo"
                },
                {
                    "label": "Small",
                    "width": 197,
                    "height": 240,
                    "source": "https://live.staticflickr.com/3321/3533453489_77de67f3af_m.jpg",
                    "url": "https://www.flickr.com/photos/cushinglibrary/3533453489/sizes/s/",
                    "media": "photo"
                },
                {
                    "label": "Small 320",
                    "width": 262,
                    "height": 320,
                    "source": "https://live.staticflickr.com/3321/3533453489_77de67f3af_n.jpg",
                    "url": "https://www.flickr.com/photos/cushinglibrary/3533453489/sizes/n/",
                    "media": "photo"
                },
                {
                    "label": "Small 400",
                    "width": 328,
                    "height": 400,
                    "source": "https://live.staticflickr.com/3321/3533453489_77de67f3af_w.jpg",
                    "url": "https://www.flickr.com/photos/cushinglibrary/3533453489/sizes/w/",
                    "media": "photo"
                },
                {
                    "label": "Medium",
                    "width": 410,
                    "height": 500,
                    "source": "https://live.staticflickr.com/3321/3533453489_77de67f3af.jpg",
                    "url": "https://www.flickr.com/photos/cushinglibrary/3533453489/sizes/m/",
                    "media": "photo"
                },
                {
                    "label": "Medium 640",
                    "width": 524,
                    "height": 640,
                    "source": "https://live.staticflickr.com/3321/3533453489_77de67f3af_z.jpg",
                    "url": "https://www.flickr.com/photos/cushinglibrary/3533453489/sizes/z/",
                    "media": "photo"
                },
                {
                    "label": "Medium 800",
                    "width": 656,
                    "height": 800,
                    "source": "https://live.staticflickr.com/3321/3533453489_77de67f3af_c.jpg",
                    "url": "https://www.flickr.com/photos/cushinglibrary/3533453489/sizes/c/",
                    "media": "photo"
                },
                {
                    "label": "Large",
                    "width": 839,
                    "height": 1024,
                    "source": "https://live.staticflickr.com/3321/3533453489_77de67f3af_b.jpg",
                    "url": "https://www.flickr.com/photos/cushinglibrary/3533453489/sizes/l/",
                    "media": "photo"
                },
                {
                    "label": "Large 1600",
                    "width": 1311,
                    "height": 1600,
                    "source": "https://live.staticflickr.com/3321/3533453489_aabf08a9d6_h.jpg",
                    "url": "https://www.flickr.com/photos/cushinglibrary/3533453489/sizes/h/",
                    "media": "photo"
                },
                {
                    "label": "Large 2048",
                    "width": 1678,
                    "height": 2048,
                    "source": "https://live.staticflickr.com/3321/3533453489_818120f873_k.jpg",
                    "url": "https://www.flickr.com/photos/cushinglibrary/3533453489/sizes/k/",
                    "media": "photo"
                },
                {
                    "label": "Original",
                    "width": 3087,
                    "height": 3767,
                    "source": "https://live.staticflickr.com/3321/3533453489_c1e692b63a_o.jpg",
                    "url": "https://www.flickr.com/photos/cushinglibrary/3533453489/sizes/o/",
                    "media": "photo"
                }
            ]
        },
        "stat": "ok"
    }
}