{
    "metadata": {
        "photo": {
            "id": "4049989255",
            "secret": "c4e25eb79d",
            "server": "3518",
            "farm": 4,
            "dateuploaded": "1256667331",
            "isfavorite": 0,
            "license": "3",
            "safety_level": "0",
            "rotation": 0,
            "originalsecret": "af9fde1627",
            "originalformat": "jpg",
            "owner": {
                "nsid": "29072716@N04",
                "username": "Cushing Memorial Library and Archives, Texas A&M",
                "realname": "",
                "location": "",
                "iconserver": "3100",
                "iconfarm": 4,
                "path_alias": "cushinglibrary",
                "gift": {
                    "gift_eligible": true,
                    "eligible_durations": [
                        "year",
                        "month",
                        "week"
                    ],
                    "new_flow": true
                }
            },
            "title": {
                "_content": "Architectual Detail - 58"
            },
            "description": {
                "_content": "<b>Title: </b>Architectual Detail - 58 \n<b>Digital Publisher: </b>Digital: Cushing Memorial Library and Archives, Texas A&amp;M University, College Station, Texas \n<b>Physical Publisher: </b>Physical: Cushing Memorial Library and Archives, Texas A&amp;M University \n<b>Description:</b> photograph date: Unknow; Architectural Detail and Misc \n<b>Date Issued:</b> 2009-09 \n<b>Format Medium: </b>2x1 \n<b>Type: </b>image \n<b>Identifier:</b> Photograph Location: Architectural Detail-58 \n<b>Rights: </b>It is the users responsibility to secure permission from the copyright holders for publication of any materials. Permission must be obtained in writing prior to publication. Please contact the Cushing Memorial Library for further information \n"
            },
            "visibility": {
                "ispublic": 1,
                "isfriend": 0,
                "isfamily": 0
            },
            "dates": {
                "posted": "1256667331",
                "taken": "2009-10-27 11:15:31",
                "takengranularity": 0,
                "takenunknown": 0,
                "lastupdate": "1421776191"
            },
            "views": "310",
            "editability": {
                "cancomment": 0,
                "canaddmeta": 0
            },
            "publiceditability": {
                "cancomment": 1,
                "canaddmeta": 1
            },
            "usage": {
                "candownload": 1,
                "canblog": 0,
                "canprint": 0,
                "canshare": 1
            },
            "comments": {
                "_content": "0"
            },
            "notes": {
                "note": []
            },
            "people": {
                "haspeople": 0
            },
            "tags": {
                "tag": []
            },
            "urls": {
                "url": [
                    {
                        "type": "photopage",
                        "_content": "https://www.flickr.com/photos/cushinglibrary/4049989255/"
                    }
                ]
            },
            "media": "photo",
            "descriptive_metadata": {
                "Title": "Architectual Detail - 58",
                "Digital Publisher": "Digital: Cushing Memorial Library and Archives, Texas A&amp;M University, College Station, Texas",
                "Physical Publisher": "Physical: Cushing Memorial Library and Archives, Texas A&amp;M University",
                "Description": "photograph date: Unknow; Architectural Detail and Misc",
                "Date Issued": "2009-09",
                "Format Medium": "2x1",
                "Type": "image",
                "Identifier": "Photograph Location: Architectural Detail-58",
                "Rights": "It is the users responsibility to secure permission from the copyright holders for publication of any materials. Permission must be obtained in writing prior to publication. Please contact the Cushing Memorial Library for further information"
            }
        },
        "stat": "ok"
    },
    "exif": {
        "photo": {
            "id": "4049989255",
            "secret": "c4e25eb79d",
            "server": "3518",
            "farm": 4,
            "camera": "",
            "exif": [
                {
                    "tagspace": "JFIF",
                    "tagspaceid": 0,
                    "tag": "JFIFVersion",
                    "label": "JFIFVersion",
                    "raw": {
                        "_content": "1.02"
                    }
                },
                {
                    "tagspace": "JFIF",
                    "tagspaceid": 0,
                    "tag": "ResolutionUnit",
                    "label": "Resolution Unit",
                    "raw": {
                        "_content": "inches"
                    }
                },
                {
                    "tagspace": "JFIF",
                    "tagspaceid": 0,
                    "tag": "XResolution",
                    "label": "X-Resolution",
                    "raw": {
                        "_content": "300"
                    },
                    "clean": {
                        "_content": "300 dpi"
                    }
                },
                {
                    "tagspace": "JFIF",
                    "tagspaceid": 0,
                    "tag": "YResolution",
                    "label": "Y-Resolution",
                    "raw": {
                        "_content": "300"
                    },
                    "clean": {
                        "_content": "300 dpi"
                    }
                }
            ]
        },
        "stat": "ok"
    },
    "comments": {
        "comments": {
            "photo_id": "4049989255"
        },
        "stat": "ok"
    },
    "sizes": {
        "sizes": {
            "canblog": 0,
            "canprint": 0,
            "candownload": 1,
            "size": [
                {
                    "label": "Square",
                    "width": 75,
                    "height": 75,
                    "source": "https://live.staticflickr.com/3518/4049989255_c4e25eb79d_s.jpg",
                    "url": "https://www.flickr.com/photos/cushinglibrary/4049989255/sizes/sq/",
                    "media": "photo"
                },
                {
                    "label": "Large Square",
                    "width": 150,
                    "height": 150,
                    "source": "https://live.staticflickr.com/3518/4049989255_c4e25eb79d_q.jpg",
                    "url": "https://www.flickr.com/photos/cushinglibrary/4049989255/sizes/q/",
                    "media": "photo"
                },
                {
                    "label": "Thumbnail",
                    "width": 66,
                    "height": 100,
                    "source": "https://live.staticflickr.com/3518/4049989255_c4e25eb79d_t.jpg",
                    "url": "https://www.flickr.com/photos/cushinglibrary/4049989255/sizes/t/",
                    "media": "photo"
                },
                {
                    "label": "Small",
                    "width": 158,
                    "height": 240,
                    "source": "https://live.staticflickr.com/3518/4049989255_c4e25eb79d_m.jpg",
                    "url": "https://www.flickr.com/photos/cushinglibrary/4049989255/sizes/s/",
                    "media": "photo"
                },
                {
                    "label": "Small 320",
                    "width": 211,
                    "height": 320,
                    "source": "https://live.staticflickr.com/3518/4049989255_c4e25eb79d_n.jpg",
                    "url": "https://www.flickr.com/photos/cushinglibrary/4049989255/sizes/n/",
                    "media": "photo"
                },
                {
                    "label": "Small 400",
                    "width": 264,
                    "height": 400,
                    "source": "https://live.staticflickr.com/3518/4049989255_c4e25eb79d_w.jpg",
                    "url": "https://www.flickr.com/photos/cushinglibrary/4049989255/sizes/w/",
                    "media": "photo"
                },
                {
                    "label": "Medium",
                    "width": 330,
                    "height": 500,
                    "source": "https://live.staticflickr.com/3518/4049989255_c4e25eb79d.jpg",
                    "url": "https://www.flickr.com/photos/cushinglibrary/4049989255/sizes/m/",
                    "media": "photo"
                },
                {
                    "label": "Original",
                    "width": 365,
                    "height": 553,
                    "source": "https://live.staticflickr.com/3518/4049989255_af9fde1627_o.jpg",
                    "url": "https://www.flickr.com/photos/cushinglibrary/4049989255/sizes/o/",
                    "media": "photo"
                }
            ]
        },
        "stat": "ok"
    }
}